[
  {
    "id": "1",
    "caption": "అలసిన కొడుకు ఆవుని ఎక్కినట్టు",
    "description": "ఇది అలసటగా ఉన్నవారు పనుల విషయంలో ఎలా చెడ్డ రీతిలో వ్యవహరిస్తారో చెబుతుంది.",
    "author": "Anonymous",
    "image": "https://via.placeholder.com/300x200.png?text=Proverb+1",
    "section": "Proverb and Entertainment",
    "upvotes": 9,
    "comments": [
      {
        "user": "Ravi",
        "text": "అర్ధం బాగుంది!",
        "reply": "edvtbedw"
      },
      {
        "user": "Anonymous",
        "text": "3r4tghyujiouytr43"
      },
      {
        "user": "Anonymous",
        "text": "drythyr3frf4r3frtgf"
      },
      {
        "user": "Anonymous",
        "text": "Oh thanks"
      },
      {
        "user": "Anonymous",
        "text": "wdeftg6434fftr3w"
      },
      {
        "user": "Anonymous",
        "text": "wedfgy7u7uhgrdfed2s2q"
      },
      {
        "user": "Anonymous",
        "text": "2e34frt6uh7i87y4ewd"
      },
      {
        "user": "Anonymous",
        "text": "wdefrgthyjjthrgefwertyu"
      },
      {
        "user": "Anonymous",
        "text": "r4t5y6u78iwdefrgthyju"
      },
      {
        "user": "Anonymous",
        "text": "xscdvbnbfazsxcdv"
      },
      {
        "user": "Anonymous",
        "text": "wdefgyhjuikujyt5r4"
      },
      {
        "user": "Anonymous",
        "text": "edcthtr2e2w"
      },
      {
        "user": "Anonymous",
        "text": "edcfde",
        "reply": ""
      },
      {
        "user": "Anonymous",
        "text": "edde",
        "reply": ""
      },
      {
        "user": "Anonymous",
        "text": "wdcfrbynytrewq",
        "reply": ""
      },
      {
        "user": "Anonymous",
        "text": "erfthyu",
        "reply": ""
      },
      {
        "user": "Anonymous",
        "text": "dvtnuht",
        "reply": ""
      }
    ]
  },
  {
    "id": "2",
    "caption": "పిల్లి లేని ఇల్లు నక్కల రాజ్యం",
    "description": "నిర్వహణ లేకపోతే చెడ్డవారు రాజ్యం చేసేవారు అని సూచిస్తుంది.",
    "author": "You",
    "image": "https://via.placeholder.com/300x200.png?text=Proverb+2",
    "section": "Proverb and Entertainment",
    "upvotes": 15,
    "comments": [
      {
        "user": "Anitha",
        "text": "నిజమే, గొప్పగా ఉంది!",
        "reply": ""
      },
      {
        "user": "Suresh",
        "text": "ఇది ఇప్పటికి కూడా వర్తిస్తుంది!",
        "reply": "ఖచ్చితంగా"
      },
      {
        "user": "Anonymous",
        "text": "wsferghtfwdw",
        "reply": ""
      },
      {
        "user": "Anonymous",
        "text": "wsferghtfwdw",
        "reply": ""
      },
      {
        "user": "Anonymous",
        "text": "wsferghtfwdw",
        "reply": ""
      },
      {
        "user": "Anonymous",
        "text": "wsferghtfwdw",
        "reply": ""
      },
      {
        "user": "Anonymous",
        "text": "wsferghtfwdw",
        "reply": ""
      },
      {
        "user": "Anonymous",
        "text": "esde",
        "reply": ""
      },
      {
        "user": "Anonymous",
        "text": "2e3r5t5r",
        "reply": ""
      },
      {
        "user": "Anonymous",
        "text": "wewd4g5t4",
        "reply": ""
      },
      {
        "user": "Anonymous",
        "text": "wded",
        "reply": ""
      },
      {
        "user": "Anonymous",
        "text": "efe",
        "reply": ""
      },
      {
        "user": "Anonymous",
        "text": "dexedc",
        "reply": ""
      },
      {
        "user": "Anonymous",
        "text": "dexrdedee",
        "reply": ""
      },
      {
        "user": "Anonymous",
        "text": " g nf ",
        "reply": ""
      },
      {
        "user": "Anonymous",
        "text": "wdf3d3w",
        "reply": ""
      },
      {
        "user": "Anonymous",
        "text": "sxes",
        "reply": ""
      },
      {
        "user": "Anonymous",
        "text": "sxsc",
        "reply": ""
      },
      {
        "user": "Anonymous",
        "text": "2e4fewd",
        "reply": ""
      },
      {
        "user": "Anonymous",
        "text": "ertghyjukjhgfedwsqa",
        "reply": ""
      },
      {
        "user": "Anonymous",
        "text": "wwerfg",
        "reply": ""
      },
      {
        "user": "Anonymous",
        "text": "bnhcgvc",
        "reply": ""
      },
      {
        "user": "Anonymous",
        "text": "nmnhbgvc n",
        "reply": ""
      },
      {
        "user": "Anonymous",
        "text": "Hey how are you??",
        "reply": ""
      }
    ]
  },
  {
    "id": "3",
    "caption": "ఎద్దు మోసిన మట్టె కాదు – మనిషి మోసిన మట్టె",
    "description": "పనుల విలువ మనుషుల శ్రమతోనే తెలుసుకోవాలి.",
    "author": "You",
    "image": "https://via.placeholder.com/300x200.png?text=Proverb+3",
    "section": "Proverb and Entertainment",
    "upvotes": 5,
    "comments": [
      {
        "user": "Anonymous",
        "text": "rgrr3r",
        "reply": ""
      }
    ]
  },
  {
    "id": "4",
    "caption": "w3ertyui",
    "description": "",
    "author": "Anonymous",
    "image": "https://via.placeholder.com/300x200.png?text=Proverb+4",
    "section": "Proverb and Entertainment",
    "upvotes": 0,
    "comments": [],
    "timestamp": "2025-08-06T11:33:30.345047"
  },
  {
    "id": "5",
    "caption": "w3ertyuiwdefrgthj",
    "description": "",
    "author": "Anonymous",
    "image": "https://via.placeholder.com/300x200.png?text=Proverb+5",
    "section": "Proverb and Entertainment",
    "upvotes": 0,
    "comments": [],
    "timestamp": "2025-08-06T11:33:36.647719"
  },
  {
    "id": "6",
    "caption": "wefg",
    "description": "",
    "author": "Anonymous",
    "image": "https://via.placeholder.com/300x200.png?text=Proverb+6",
    "section": "Proverb and Entertainment",
    "upvotes": 0,
    "comments": [],
    "timestamp": "2025-08-06T11:35:49.117902"
  },
  {
    "id": "7",
    "caption": "df",
    "description": "",
    "author": "Anonymous",
    "image": "https://via.placeholder.com/300x200.png?text=Proverb+7",
    "section": "Proverb and Entertainment",
    "upvotes": 0,
    "comments": [],
    "timestamp": "2025-08-06T11:36:05.827132"
  },
  {
    "id": "8",
    "caption": "qswedc",
    "description": "",
    "author": "Anonymous",
    "image": "https://via.placeholder.com/300x200.png?text=Proverb+8",
    "section": "Proverb and Entertainment",
    "upvotes": 0,
    "comments": [],
    "timestamp": "2025-08-06T11:46:59.971869"
  },
  {
    "id": "9",
    "caption": "werfgth",
    "description": "",
    "author": "Anonymous",
    "image": "https://via.placeholder.com/300x200.png?text=Proverb+9",
    "section": "Proverb and Entertainment",
    "upvotes": 0,
    "comments": [],
    "timestamp": "2025-08-06T11:48:40.023245"
  },
  {
    "id": "10",
    "caption": "r34t5y6uj",
    "description": "",
    "author": "Anonymous",
    "image": "https://via.placeholder.com/300x200.png?text=Proverb+10",
    "section": "Proverb and Entertainment",
    "upvotes": 0,
    "comments": [],
    "timestamp": "2025-08-06T11:49:20.950323"
  },
  {
    "id": "11",
    "caption": "qwerftgyh",
    "description": "",
    "author": "Anonymous",
    "image": "https://via.placeholder.com/300x200.png?text=Proverb+11",
    "section": "Proverb and Entertainment",
    "upvotes": 0,
    "comments": [],
    "timestamp": "2025-08-06T11:52:30.120142"
  },
  {
    "id": "12",
    "caption": "defrgthynujk,mnhgfdwq",
    "description": "",
    "author": "Anonymous",
    "image": "https://via.placeholder.com/300x200.png?text=Proverb+12",
    "section": "Proverb and Entertainment",
    "upvotes": 0,
    "comments": [],
    "timestamp": "2025-08-06T11:54:00.662198"
  },
  {
    "id": "13",
    "caption": "qefvg",
    "description": "",
    "author": "Anonymous",
    "image": "https://via.placeholder.com/300x200.png?text=Proverb+13",
    "section": "Proverb and Entertainment",
    "upvotes": 0,
    "comments": [],
    "timestamp": "2025-08-06T11:55:19.576105"
  },
  {
    "id": "14",
    "caption": "wedfrgtyhujk,l",
    "description": "",
    "author": "Anonymous",
    "image": "https://via.placeholder.com/300x200.png?text=Proverb+14",
    "section": "Proverb and Entertainment",
    "upvotes": 0,
    "comments": [],
    "timestamp": "2025-08-06T11:56:30.349394"
  },
  {
    "id": "15",
    "caption": "wedfrgtyhujk,l",
    "description": "",
    "author": "Anonymous",
    "image": "https://via.placeholder.com/300x200.png?text=Proverb+15",
    "section": "Proverb and Entertainment",
    "upvotes": 0,
    "comments": [],
    "timestamp": "2025-08-06T11:56:37.079956"
  },
  {
    "id": "16",
    "caption": "wedrfg",
    "description": "",
    "author": "Anonymous",
    "image": "https://via.placeholder.com/300x200.png?text=Proverb+16",
    "section": "Proverb and Entertainment",
    "upvotes": 1,
    "comments": [
      {
        "user": "a",
        "text": "edctvybu",
        "reply": ""
      }
    ],
    "timestamp": "2025-08-06T11:57:35.245514"
  },
  {
    "id": "17",
    "caption": "efrgtyh",
    "description": "",
    "author": "Anonymous",
    "image": "https://via.placeholder.com/300x200.png?text=Proverb+17",
    "section": "Proverb and Entertainment",
    "upvotes": 0,
    "comments": [],
    "timestamp": "2025-08-06T11:58:43.052422"
  },
  {
    "id": "18",
    "caption": "efrgtyhwdefrtghn bvfcd",
    "description": "",
    "author": "Anonymous",
    "image": "https://via.placeholder.com/300x200.png?text=Proverb+18",
    "section": "Proverb and Entertainment",
    "upvotes": 0,
    "comments": [],
    "timestamp": "2025-08-06T11:59:23.625784"
  },
  {
    "id": "19",
    "caption": "Every Dog Has it's Day",
    "description": "",
    "author": "Anonymous",
    "image": "https://via.placeholder.com/300x200.png?text=Proverb+19",
    "section": "Proverb and Entertainment",
    "upvotes": 1,
    "comments": [],
    "timestamp": "2025-08-06T12:01:14.332998"
  },
  {
    "id": "20",
    "caption": "Every Dog Has it's Day",
    "description": "",
    "author": "Anonymous",
    "image": "https://via.placeholder.com/300x200.png?text=Proverb+20",
    "section": "Proverb and Entertainment",
    "upvotes": 1,
    "comments": [],
    "timestamp": "2025-08-06T12:01:19.066795"
  },
  {
    "id": "21",
    "caption": "Every Dog Has it's Day",
    "description": "",
    "author": "Anonymous",
    "image": "https://via.placeholder.com/300x200.png?text=Proverb+21",
    "section": "Proverb and Entertainment",
    "upvotes": 0,
    "comments": [],
    "timestamp": "2025-08-06T12:01:53.512688"
  },
  {
    "id": "22",
    "caption": "erfg",
    "description": "",
    "author": "Anonymous",
    "image": "https://via.placeholder.com/300x200.png?text=Proverb+22",
    "section": "Proverb and Entertainment",
    "upvotes": 0,
    "comments": [],
    "timestamp": "2025-08-06T12:07:00.174282"
  },
  {
    "id": "23",
    "caption": "werfgthyjui8u7654rfvghji8u7654redfghu7654rdfghu765r4fvghnji8765rfvg",
    "description": "",
    "author": "Anonymous",
    "image": "https://via.placeholder.com/300x200.png?text=Proverb+23",
    "section": "Proverb and Entertainment",
    "upvotes": 0,
    "comments": [
      {
        "user": "Ravi",
        "text": "అర్ధం బాగుంది!",
        "reply": "edvtbedw"
      },
      {
        "user": "Anonymous",
        "text": "2w3e4rt6y7u8i9u7y6tr"
      },
      {
        "user": "Ravi",
        "text": "అర్ధం బాగుంది!",
        "reply": "edvtbedw"
      },
      {
        "user": "Anonymous",
        "text": "Ajay Kumar Madaka"
      }
    ],
    "timestamp": "2025-08-07T00:14:59.036943"
  },
  {
    "id": "24",
    "caption": "qwsderthyuikjmhgfd",
    "description": "",
    "author": "Anonymous",
    "image": "https://via.placeholder.com/300x200.png?text=Proverb+24",
    "section": "Proverb and Entertainment",
    "upvotes": 0,
    "comments": [],
    "timestamp": "2025-08-07T20:32:17.537936"
  },
  {
    "id": "25",
    "caption": "erthyjuikjhgtfrdews",
    "description": "",
    "author": "Anonymous",
    "image": "https://via.placeholder.com/300x200.png?text=Proverb+25",
    "section": "Proverb and Entertainment",
    "upvotes": 0,
    "comments": [],
    "timestamp": "2025-08-07T20:32:55.990146"
  },
  {
    "id": "26",
    "caption": "Nature is for Humans' need not for  Naveen's Greed",
    "description": "",
    "author": "qwertyuiop",
    "image": "https://via.placeholder.com/300x200.png?text=Proverb+26",
    "section": "Proverb and Entertainment",
    "upvotes": 0,
    "comments": [],
    "timestamp": "2025-08-08T09:43:50.383839"
  },
  {
    "id": "27",
    "caption": "చెడపకురా చెడేవూ",
    "description": "",
    "author": "a",
    "image": "https://via.placeholder.com/300x200.png?text=Proverb+27",
    "section": "Proverb and Entertainment",
    "upvotes": 1,
    "comments": [],
    "timestamp": "2025-08-08T15:35:58.720229"
  }
]